{
    "links":[
        {
            "value": "#",
            "name": "Home",
            "id": 1
        },
        {
            "value": "#",
            "name": "Who We Are",
            "id": 2
        },
        {
            "value": "#",
            "name": "What We Do",
            "id": 3
        },
        {
            "value": "#",
            "name": "Where We Work",
            "id": 4
        },
        {
            "value": "#",
            "name": "Careers",
            "id": 5
        },
        {
            "value": "#",
            "name": "News",
            "id": 6
        },
        {
            "value": "#",
            "name": "Get In Touch Now",
            "id": 7
        }
    ],

    "cards":[
        {
            "type": "template",
            "mainText": "Establish Goals",
            "bottomText": "Lorem ipsum dolor, sit amet consectetur adipisicing elit. Pariatur tempore, atque enim culpa necessitatibus praesentium cumque fuga voluptatibus nemo non.",
            "iconClass": "fas fa-road",
            "id": 1
        },
        {
            "type": "template",
            "mainText": "Work With a Team",
            "bottomText": "Lorem ipsum dolor, sit amet consectetur adipisicing elit. Pariatur tempore, atque enim culpa necessitatibus praesentium cumque fuga voluptatibus nemo non.",
            "iconClass": "fas fa-video",
            "id": 2
        },
        {
            "type": "template",
            "mainText": "Get Results",
            "bottomText": "Lorem ipsum dolor, sit amet consectetur adipisicing elit. Pariatur tempore, atque enim culpa necessitatibus praesentium cumque fuga voluptatibus nemo non.",
            "iconClass": "fas fa-tint",
            "id": 3
        },
        {
            "type": "services",
            "mainText": "Google SEO",
            "bottomText": "Lorem ipsum dolor, sit amet consectetur adipisicing elit. Pariatur tempore, atque enim culpa necessitatibus praesentium cumque fuga voluptatibus nemo non.",
            "iconClass": "fab fa-google",
            "id": 4
        },
        {
            "type": "services",
            "mainText": "Brand Strategy",
            "bottomText": "Lorem ipsum dolor, sit amet consectetur adipisicing elit. Pariatur tempore, atque enim culpa necessitatibus praesentium cumque fuga voluptatibus nemo non.",
            "iconClass": "fas fa-cog",
            "id": 5
        },
        {
            "type": "services",
            "mainText": "GLocal SEo",
            "bottomText": "Lorem ipsum dolor, sit amet consectetur adipisicing elit. Pariatur tempore, atque enim culpa necessitatibus praesentium cumque fuga voluptatibus nemo non.",
            "iconClass": "fas fa-building",
            "id": 6
        },
        {
            "type": "services",
            "mainText": "Seo Analysis",
            "bottomText": "Lorem ipsum dolor, sit amet consectetur adipisicing elit. Pariatur tempore, atque enim culpa necessitatibus praesentium cumque fuga voluptatibus nemo non.",
            "iconClass": "fas fa-chart-bar",
            "id": 7
        },
        {
            "type": "plans",
            "mainText": "Standard",
            "price": 19,
            "perks": ["5", "5 GB", "Unlimited"],
            "id": 8
        },
        {
            "type": "plans",
            "mainText": "Premium",
            "price": 29,
            "perks": ["10", "15 GB", "Unlimited"],
            "id": 9
        },
        {
            "type": "plans",
            "mainText": "Professional",
            "price": 39,
            "perks": ["15", "30 GB", "Unlimited"],
            "id": 10
        },
        {
            "type": "plans",
            "mainText": "Extreme",
            "price": 59,
            "perks": ["Unlimited", "Unlimited", "Unlimited"],
            "id": 11
        },
        {
            "type": "news",
            "image": "related-service-2-700x441.jpg",
            "mainText": "Why You Need A SEO Agency Now",
            "date": "November 1st, 2017",
            "bottomText": "Lorem ipsum dolor, sit amet consectetur adipisicing elit. Pariatur tempore, atque enim culpa necessitatibus praesentium cumque fuga voluptatibus nemo non.",
            "id": 12
        },
        {
            "type": "news",
            "image": "related-service-4-700x441.jpg",
            "mainText": "SEO Tips For Your Startup",
            "date": "November 1st, 2017",
            "bottomText": "Lorem ipsum dolor, sit amet consectetur adipisicing elit. Pariatur tempore, atque enim culpa necessitatibus praesentium cumque fuga voluptatibus nemo non.",
            "id": 13
        },
        {
            "type": "news",
            "image": "blog-post-6-700x441.jpg",
            "mainText": "Image Optimization For Your Site",
            "date": "November 1st, 2017",
            "bottomText": "Lorem ipsum dolor, sit amet consectetur adipisicing elit. Pariatur tempore, atque enim culpa necessitatibus praesentium cumque fuga voluptatibus nemo non.",
            "id": 14
        },
        {
            "type": "clients",
            "image": "testimonials-2.jpg",
            "name": "Luis Desalvo",
            "position": "creo tech",
            "review": "Ability proceeds from a fusion of skills, knowledge, understanding and imagination, consolidated by experience.",
            "id": 15
        },
        {
            "type": "clients",
            "image": "testimonials-1.jpg",
            "name": "Sheila McCourtney",
            "position": "architect",
            "review": "Beauty is when you can appreciate yourself. When you love yourself, that’s when you’re most beautiful.",
            "id": 16
        }
    ],

    "images":[
        {
            "id":1,
            "name": "case-study-gallery-3-1.jpg"
        },
        {
            "id":2,
            "name": "case-study-gallery-2.jpg"
        },
        {
            "id":3,
            "name": "case-study-gallery-4-1.jpg"
        },
        {
            "id":4,
            "name": "case-study-gallery-5-1.jpg"
        },
        {
            "id":5,
            "name": "case-study-gallery-6-1.jpg"
        },
        {
            "id":6,
            "name": "case-study-gallery-3-1.jpg"
        }
    ],

    "partners":[
        {
            "id": 1,
            "name": "clients_partner_1-200x202.png"
        },
        {
            "id": 2,
            "name": "clients_partner_2-200x202.png"
        },
        {
            "id": 3,
            "name": "clients_partner_3-200x202.png"
        },
        {
            "id": 4,
            "name": "clients_partner_4-200x202.png"
        },
        {
            "id": 5,
            "name": "clients_partner_5-200x202.png"
        },
        {
            "id": 6,
            "name": "clients_partner_6-200x202.png"
        }
    ]
}